autil/__init__.py
autil/alt_plot.py
autil/country2continent.py
autil/io.py
autil/io_download.py
autil/io_parquet.py
autil/ipy_addpath.py
autil/ipy_displays.py
autil/ipy_print.py
autil/lm_lighten.py
autil/mpl_plot.py
autil/mpl_set.py
autil/owari.py
autil/pd_clean.py
autil/pd_perform.py
autil/pd_table.py
autil/print.py
autil/scrape.py
autil/scrape_proxy.py
autil/sendmail.py
autil/sk_metrics.py
autil/sqlite.py
autil/stat_summary.py
autil/tex_table.py
autil/tr.py
autil/z2h.py
autil-0.2.4.dist-info/METADATA
autil-0.2.4.dist-info/WHEEL
autil-0.2.4.dist-info/RECORD
