Metadata-Version: 2.1
Name: autil
Version: 0.2.4
Summary: Some Python snippets for a researcher's daily use
Author: alalalalaki
Author-email: harlan.zhu@gmail.com
Requires-Python: >=3.8,<4.0
Classifier: Programming Language :: Python :: 3
Classifier: Programming Language :: Python :: 3.8
Classifier: Programming Language :: Python :: 3.9
Classifier: Programming Language :: Python :: 3.10
Classifier: Programming Language :: Python :: 3.11
Requires-Dist: adjustText (>=0.7.3,<0.8.0)
Requires-Dist: altair (>=4.1,<5.0)
Requires-Dist: country_converter (>=0.7.3,<0.8.0)
Requires-Dist: cycler (>=0.10,<0.11)
Requires-Dist: deepl (>=1.6.0,<2.0.0)
Requires-Dist: linearmodels (>=4.24,<5.0)
Requires-Dist: matplotlib (>=3.4,<4.0)
Requires-Dist: matplotlib-label-lines (>=0.5.1,<0.6.0)
Requires-Dist: numpy (>=1.21,<2.0)
Requires-Dist: pandas (>=1.3,<2.0)
Requires-Dist: pyarrow (>=5.0.0,<6.0.0)
Requires-Dist: pycountry_convert (>=0.7.2,<0.8.0)
Requires-Dist: requests (>=2.26,<3.0)
Requires-Dist: requests_html (>=0.10,<0.11)
Requires-Dist: scikit_learn (>=1.0,<2.0)
Requires-Dist: seaborn (>=0.11,<0.12)
Requires-Dist: selenium (>=3.141.0,<4.0.0)
Requires-Dist: selenium-wire (>=4.6,<5.0)
Requires-Dist: tenacity (>=8.0.1,<9.0.0)
Requires-Dist: tqdm (>=4.62,<5.0)
Requires-Dist: translators (>=4.9.5,<5.0.0)
